{
  "store_id": "canva",
  "updated_at": "2026-06-16T12:16:25Z",
  "codes": [
    {
      "code": "MEMDAY50",
      "description": "Memorial Day: 50% off Canva Pro annual",
      "scraped_at": "2026-06-16T12:16:25Z",
      "ai_score": 0,
      "best_deal": true,
      "thumbs_up": 0,
      "thumbs_down": 0
    },
    {
      "code": "CANVAPRO",
      "description": "45% off Canva Pro annual",
      "scraped_at": "2026-06-16T12:16:25Z",
      "ai_score": 0,
      "best_deal": false,
      "thumbs_up": 0,
      "thumbs_down": 0
    },
    {
      "code": "DESIGN20",
      "description": "20% off Pro plan",
      "scraped_at": "2026-06-16T12:16:25Z",
      "ai_score": 0,
      "best_deal": false,
      "thumbs_up": 0,
      "thumbs_down": 0
    },
    {
      "code": "CANVASAVE",
      "description": "First month Pro free",
      "scraped_at": "2026-06-16T12:16:25Z",
      "ai_score": 0,
      "best_deal": false,
      "thumbs_up": 0,
      "thumbs_down": 0
    },
    {
      "code": "CANVATEAM",
      "description": "30% off Canva Teams",
      "scraped_at": "2026-06-16T12:16:25Z",
      "ai_score": 0,
      "best_deal": false,
      "thumbs_up": 0,
      "thumbs_down": 0
    },
    {
      "code": "CANVABIZ",
      "description": "25% off Business annual plan",
      "scraped_at": "2026-06-16T12:16:25Z",
      "ai_score": 0,
      "best_deal": false,
      "thumbs_up": 0,
      "thumbs_down": 0
    },
    {
      "code": "CANVASTUD",
      "description": "Free Canva Pro for students",
      "scraped_at": "2026-06-16T12:16:25Z",
      "ai_score": 0,
      "best_deal": false,
      "thumbs_up": 0,
      "thumbs_down": 0
    },
    {
      "code": "CANVAEDU",
      "description": "Free Canva for Education",
      "scraped_at": "2026-06-16T12:16:25Z",
      "ai_score": 0,
      "best_deal": false,
      "thumbs_up": 0,
      "thumbs_down": 0
    },
    {
      "code": "CANVAPRINT",
      "description": "10% off Canva Print orders",
      "scraped_at": "2026-06-16T12:16:25Z",
      "ai_score": 0,
      "best_deal": false,
      "thumbs_up": 0,
      "thumbs_down": 0
    }
  ],
  "ai_deals": []
}